fmslist/__init__.py
fmslist/items.py
fmslist/utils.py
fmslist-0.0.12.dist-info/METADATA
fmslist-0.0.12.dist-info/WHEEL
fmslist-0.0.12.dist-info/licenses/LICENSE
fmslist-0.0.12.dist-info/RECORD
