Metadata-Version: 2.4
Name: fmslist
Version: 0.0.12
Summary: A web scraper that lists items from Findmestore.
Project-URL: Homepage, https://github.com/d4n1elchen/fmslist
Project-URL: Issues, https://github.com/d4n1elchen/fmslist/issues
License-Expression: MIT
License-File: LICENSE
Requires-Python: >=3.13
Requires-Dist: bs4
Requires-Dist: pytz
Requires-Dist: requests
